[
  { "id": 1, "value": "Buick", "label": "Buick" },
  { "id": 2, "value": "Volvo", "label": "Volvo" },
  { "id": 3, "value": "HUMMER", "label": "HUMMER" },
  { "id": 4, "value": "Subaru", "label": "Subaru" },
  { "id": 5, "value": "Mitsubishi", "label": "Mitsubishi" },
  { "id": 6, "value": "Nissan", "label": "Nissan" },
  { "id": 7, "value": "Lincoln", "label": "Lincoln" },
  { "id": 8, "value": "GMC", "label": "GMC" },
  { "id": 9, "value": "Hyundai", "label": "Hyundai" },
  { "id": 10, "value": "MINI", "label": "MINI" },
  { "id": 11, "value": "Bentley", "label": "Bentley" },
  { "id": 12, "value": "Mercedes-Benz", "label": "Mercedes-Benz" },
  { "id": 13, "value": "Aston Martin", "label": "Aston Martin" },
  { "id": 14, "value": "Pontiac", "label": "Pontiac" },
  { "id": 15, "value": "Lamborghini", "label": "Lamborghini" },
  { "id": 16, "value": "Audi", "label": "Audi" },
  { "id": 17, "value": "BMW", "label": "BMW" },
  { "id": 18, "value": "Chevrolet", "label": "Chevrolet" },
  { "id": 19, "value": "Chrysler", "label": "Chrysler" },
  { "id": 20, "value": "Kia", "label": "Kia" },
  { "id": 21, "value": "Land", "label": "Land" }
]
